jsondbin/__init__.py
jsondbin/config.py
jsondbin/logic/__init__.py
jsondbin/logic/base.py
jsondbin/logic/collection.py
jsondbin/logic/document.py
jsondbin/logic/schema.py
jsondbin/models/__init__.py
jsondbin/models/collection.py
jsondbin/models/document.py
jsondbin/models/error.py
jsondbin-0.1.2.dist-info/LICENSE
jsondbin-0.1.2.dist-info/METADATA
jsondbin-0.1.2.dist-info/WHEEL
jsondbin-0.1.2.dist-info/top_level.txt
jsondbin-0.1.2.dist-info/RECORD
