Metadata-Version: 2.1
Name: jsondbin
Version: 0.1.2
Summary: Unified Interface for JSON Database with jsonbin.io
Home-page: https://github.com/subhayu99/jsondbin
Author: Subhayu Kumar Bala
Author-email: balasubhayu99@gmail.com
Classifier: Development Status :: 3 - Alpha
Classifier: Intended Audience :: Developers
Classifier: License :: OSI Approved :: MIT License
Classifier: Programming Language :: Python :: 3
Classifier: Programming Language :: Python :: 3.6
Classifier: Programming Language :: Python :: 3.7
Classifier: Programming Language :: Python :: 3.8
Requires-Python: >=3.6
License-File: LICENSE
